LICENSE
README.md
pyproject.toml
setup.cfg
./mc10/__init__.py
./mc10/bastoc10.py
./mc10/c10.py
./mc10/c10tobas.py
./mc10/mcbasic.py
./mc10/mclex.py
./tests/conftest.py
./tests/mc10/resources/__init__.py
mc10/__init__.py
mc10/bastoc10.py
mc10/c10.py
mc10/c10tobas.py
mc10/mcbasic.py
mc10/mclex.py
mc10_tools.egg-info/PKG-INFO
mc10_tools.egg-info/SOURCES.txt
mc10_tools.egg-info/dependency_links.txt
mc10_tools.egg-info/entry_points.txt
mc10_tools.egg-info/requires.txt
mc10_tools.egg-info/top_level.txt
tests/conftest.py
tests/mc10/resources/__init__.py