Metadata-Version: 2.4
Name: mc10-tools
Version: 0.9
Summary: Set of MC-10 tools
Author-email: Jamie Cho <jamieleecho+mc10-tools@gmail.com>
License-Expression: MIT
Project-URL: Repository, https://github.com/jamieleecho/mc10-tools
Project-URL: Issues, https://github.com/jamieleecho/mc10-tools/issues
Keywords: coco,image,conversion,trs-80,tandy
Classifier: Development Status :: 3 - Alpha
Classifier: Intended Audience :: Developers
Classifier: Topic :: Software Development :: Build Tools
Classifier: Programming Language :: Python :: 3
Requires-Python: >=3.9.19
License-File: LICENSE
Requires-Dist: click>=7.1.3
Requires-Dist: ply>=3.11
Dynamic: license-file
